blueprintflow/__init__.py
blueprintflow-0.0.0.dist-info/LICENSE
blueprintflow-0.0.0.dist-info/METADATA
blueprintflow-0.0.0.dist-info/WHEEL
blueprintflow-0.0.0.dist-info/top_level.txt
blueprintflow-0.0.0.dist-info/RECORD
