Metadata-Version: 2.2
Name: blueprintflow
Version: 0.0.0
Summary: Simplify code generation via abstractions and structured retrieval
Author: oceord
License: MIT License
Project-URL: Repository, https://github.com/oceord/blueprintflow
Classifier: License :: OSI Approved :: MIT License
Classifier: Programming Language :: Python :: 3 :: Only
Classifier: Programming Language :: Python :: 3.12
Classifier: Programming Language :: Python :: 3.13
Classifier: Topic :: Software Development :: Libraries :: Python Modules
Classifier: Topic :: Scientific/Engineering :: Artificial Intelligence
Classifier: Topic :: Software Development :: Code Generators
Classifier: Development Status :: 1 - Planning
Requires-Python: >=3.12
License-File: LICENSE
